[
	{
		"id": 1323,
		"title": "Ratt",
		"author_id": 297417,
		"author_name": "rorie1983",
		"timestamp": "2005-05-11T03:51:35.000Z",
		"content": "who is a fan of this heavy metal group, i'm not a real fan yet<br />the only song i've heard is shame,shame.shame, there's a video clip to it on [url=http://music.yahoo.com/]yahoo! launch[/url][url=http://www.dosvault.tk][img]http://venus.walagata.com/w/thedosvault/sig/tdv_banner.jpg[/img][/url]<br /><br />[url=http://s4.invisionfree.com/The_Dos_Vault_Forum]The Dos Vault Forum needs members[/url]"
	}
]
