[
	{
		"id": 504,
		"title": "Commander Keen comic poster",
		"author_id": 1486808,
		"author_name": "Galaxieretter",
		"timestamp": "2005-06-29T20:07:20.000Z",
		"content": "I made a \"poster\" of my upcoming comic that I never get my butt to around completing. I would of looked better but I was trying out a new drawing program (open canvas) but ended up coloring it in Photoshop because it was crap.<br /><br />[img]http://img276.echo.cx/img276/6747/poster13ws.png[/img]<br /><br />The title of the series I am working on is called \"Commander Keen and the Triquantifier Machine\"-----------------------<br />\"The Adventures of Commander Keen\" issue #1: coming soon."
	},
	{
		"id": 13808,
		"title": "Re: Commander Keen comic poster",
		"author_id": 1485753,
		"author_name": "KeenRush",
		"timestamp": "2005-06-29T20:12:28.000Z",
		"content": "Whoaly garg! [img]http://www.classicgaming.com/cc314/msgboard/emotikeen-garg.gif[/img]  Looks awesome, can't wait for the comics! Cool name, as well.<b>You hear in your mind: GAAARRRRRGG!</b>"
	},
	{
		"id": 13809,
		"title": "Re: Commander Keen comic poster",
		"author_id": 1485695,
		"author_name": "Genius314",
		"timestamp": "2005-06-29T23:34:59.000Z",
		"content": "[img]http://www.classicgaming.com/cc314/msgboard/emotikeen-smile.gif[/img]  [img]http://www.classicgaming.com/cc314/msgboard/emotikeen-surprise.gif[/img]  [img]http://www.classicgaming.com/cc314/msgboard/emotikeen-drool.gif[/img] <br /><br /><br /><br /><br />Cool.[img]http://img.photobucket.com/albums/v609/genius314/picturekeen.bmp[/img]"
	},
	{
		"id": 13810,
		"title": "Re: Commander Keen comic poster",
		"author_id": 1486477,
		"author_name": "Mr12000",
		"timestamp": "2005-07-09T00:56:35.000Z",
		"content": "ugly! wow it sucks! stop posting this filth!<br /><br /><br />just kidding [img]http://www.classicgaming.com/cc314/msgboard/emotikeen-cheeky.gif[/img]  it looks awesome!!!!"
	},
	{
		"id": 13811,
		"title": "Re: Commander Keen comic poster",
		"author_id": 1486547,
		"author_name": "Harvey",
		"timestamp": "2005-07-09T12:24:17.000Z",
		"content": "Wow, it looks cool![img]http://www.classicgaming.com/cc314/msgboard/emotikeen-surprise.gif[/img]  Can't wait for the comic series![img]http://www.classicgaming.com/cc314/msgboard/emotikeen-grin.gif[/img] [img]http://images.ucomics.com/comics/ga/2005/ga050705.gif[/img]"
	}
]
