[
	{
		"id": 278,
		"title": "problem...",
		"author_id": 1486896,
		"author_name": "bp",
		"timestamp": "2005-06-24T20:20:36.000Z",
		"content": "my 3D game will be postponed until I get a new cd player. <br />                            can I get help?!"
	},
	{
		"id": 8142,
		"title": "Re: problem...",
		"author_id": 1486240,
		"author_name": "grafix5000",
		"timestamp": "2005-06-24T20:47:56.000Z",
		"content": "[img]http://www.classicgaming.com/cc314/msgboard/emotikeen-confused.gif[/img] <br /><br />Do you mean a CD drive? And what do you need help with?<font color=\"BLACK\"><br />My [url=http://kevan.org/brain.cgi?grafix5000]MindBending Power[/url] is 5.43 points.<br />Possibly the [url=http://legion.gibbering.net/misterx/troutwar.php?s=grafix5000]funniest thing[/url] on the interweb.<br />Go to [url=http://www.toxicsheep.com]www.toxicsheep.com[/url] to see my site!<br /></font><br />[img]http://www.toxicsheep.com/sigs/scrobblersig.php[/img]"
	},
	{
		"id": 8143,
		"title": "Re: problem...",
		"author_id": 1485753,
		"author_name": "KeenRush",
		"timestamp": "2005-06-24T21:10:05.000Z",
		"content": "Probably help with the 3D Keen game.. Sorry, can't help. [img]http://www.classicgaming.com/cc314/msgboard/emotikeen-mort.gif[/img] <b>You hear in your mind: GAAARRRRRGG!</b>"
	},
	{
		"id": 8144,
		"title": "Re: problem...",
		"author_id": 989154,
		"author_name": "Djaser",
		"timestamp": "2005-06-27T13:08:43.000Z",
		"content": "Yes ofcourse I can help. I'll send a new cd player right away. Should it be able to play dvd, stereo installition, yes?-----------------<br />[img]http://www.jamba.nl/storage/view/upload/logo/image_multijpeg/DevilFrogVerwandlung.jpg[/img][img]http://www.jamster.com/s/jiw/img/US_logo_big.gif[/img]<br />Jamster! rules!"
	},
	{
		"id": 8145,
		"title": "ummm",
		"author_id": 1486896,
		"author_name": "bp",
		"timestamp": "2005-07-01T23:47:38.000Z",
		"content": "I need the Dark Basic cd to make it,[img]http://www.classicgaming.com/cc314/msgboard/emotikeen-smile.gif[/img] <br /><br />yes cd -DRIVE-<br /><br />really?! youd send me one :dope keen"
	},
	{
		"id": 8146,
		"title": "Re: ummm",
		"author_id": 1486240,
		"author_name": "grafix5000",
		"timestamp": "2005-07-02T06:40:34.000Z",
		"content": "No, he was being sarcastic. You can buy a CD drive at a computer store for about $10, so it shouldn't be to difficult to get one."
	},
	{
		"id": 8147,
		"title": "hey,",
		"author_id": 1486896,
		"author_name": "bp",
		"timestamp": "2005-07-02T12:58:34.000Z",
		"content": "I know he was don't you see the dope keen? <br />(In words, must have typed it wrong.....)"
	},
	{
		"id": 8148,
		"title": "Re:  hey,",
		"author_id": 1486240,
		"author_name": "grafix5000",
		"timestamp": "2005-07-02T13:21:40.000Z",
		"content": "I didn't see the mistyped :dope keen, mainly because I don't read posts slowly and so skip over anything irrelevant. Now I look rather stupid. Oops. [img]http://www.classicgaming.com/cc314/msgboard/emotikeen-embarrassed.gif[/img]"
	},
	{
		"id": 8149,
		"title": "Re:  hey,",
		"author_id": 1486493,
		"author_name": "Superadammario64",
		"timestamp": "2005-07-07T17:40:52.000Z",
		"content": "you could try getting a gmail account and host your files on there since you get like 2gb worth of space. That could help until you get a new cd drive. I do have some invites if you want it.The end is near. An evil force returns. And only Commander Keen can stop him, but this time he must team up with a super sonic hedgehog and a two tailed fox. Follow the adventure:[url=http://www.geocities.com/superadammario/chaos.html]Dimension Chaos[/url]<br />A Commander Keen and Sonic The Hedgehog Crossover Fan Fiction<br /><br />Visit my website at [url=http://www.geocities.com/superadammario]www.geocities.com/superadammario[/url]"
	},
	{
		"id": 8150,
		"title": "Re:  hey,",
		"author_id": 1486240,
		"author_name": "grafix5000",
		"timestamp": "2005-07-07T18:43:13.000Z",
		"content": "The problem is that he can't use the DarkBasic CD without a working CD drive, not that he doesn't have storage space. [img]http://www.classicgaming.com/cc314/msgboard/emotikeen-crazy.gif[/img]"
	},
	{
		"id": 8151,
		"title": "Re:  hey,",
		"author_id": 1486493,
		"author_name": "Superadammario64",
		"timestamp": "2005-07-07T20:53:57.000Z",
		"content": "oh my bad then [img]http://www.classicgaming.com/cc314/msgboard/emotikeen-dead.gif[/img] The end is near. An evil force returns. And only Commander Keen can stop him, but this time he must team up with a super sonic hedgehog and a two tailed fox. Follow the adventure:[url=http://www.geocities.com/superadammario/chaos.html]Dimension Chaos[/url]<br />A Commander Keen and Sonic The Hedgehog Crossover Fan Fiction<br /><br />Visit my website at [url=http://www.geocities.com/superadammario]www.geocities.com/superadammario[/url]"
	}
]
