[
	{
		"id": 15554,
		"title": "Unknown",
		"author_id": 0,
		"author_name": "Anonymous",
		"timestamp": "2004-12-31T22:00:00.000Z",
		"content": "(This post is missing and can not be restored)"
	},
	{
		"id": 15555,
		"title": "Unknown",
		"author_id": 0,
		"author_name": "Anonymous",
		"timestamp": "2004-12-31T22:00:00.000Z",
		"content": "(This post is missing and can not be restored)"
	},
	{
		"id": 15556,
		"title": "Unknown",
		"author_id": 0,
		"author_name": "Anonymous",
		"timestamp": "2004-12-31T22:00:00.000Z",
		"content": "(This post is missing and can not be restored)"
	},
	{
		"id": 15557,
		"title": "Unknown",
		"author_id": 0,
		"author_name": "Anonymous",
		"timestamp": "2004-12-31T22:00:00.000Z",
		"content": "(This post is missing and can not be restored)"
	},
	{
		"id": 15558,
		"title": "Unknown",
		"author_id": 0,
		"author_name": "Anonymous",
		"timestamp": "2004-12-31T22:00:00.000Z",
		"content": "(This post is missing and can not be restored)"
	},
	{
		"id": 15559,
		"title": "Unknown",
		"author_id": 0,
		"author_name": "Anonymous",
		"timestamp": "2004-12-31T22:00:00.000Z",
		"content": "(This post is missing and can not be restored)"
	},
	{
		"id": 15560,
		"title": "Unknown",
		"author_id": 0,
		"author_name": "Anonymous",
		"timestamp": "2004-12-31T22:00:00.000Z",
		"content": "(This post is missing and can not be restored)"
	},
	{
		"id": 15561,
		"title": "Unknown",
		"author_id": 0,
		"author_name": "Anonymous",
		"timestamp": "2004-12-31T22:00:00.000Z",
		"content": "(This post is missing and can not be restored)"
	},
	{
		"id": 15562,
		"title": "Unknown",
		"author_id": 0,
		"author_name": "Anonymous",
		"timestamp": "2004-12-31T22:00:00.000Z",
		"content": "(This post is missing and can not be restored)"
	},
	{
		"id": 15563,
		"title": "Unknown",
		"author_id": 0,
		"author_name": "Anonymous",
		"timestamp": "2004-12-31T22:00:00.000Z",
		"content": "(This post is missing and can not be restored)"
	},
	{
		"id": 15564,
		"title": "Unknown",
		"author_id": 0,
		"author_name": "Anonymous",
		"timestamp": "2004-12-31T22:00:00.000Z",
		"content": "(This post is missing and can not be restored)"
	},
	{
		"id": 15565,
		"title": "Unknown",
		"author_id": 0,
		"author_name": "Anonymous",
		"timestamp": "2004-12-31T22:00:00.000Z",
		"content": "(This post is missing and can not be restored)"
	},
	{
		"id": 15566,
		"title": "Unknown",
		"author_id": 0,
		"author_name": "Anonymous",
		"timestamp": "2004-12-31T22:00:00.000Z",
		"content": "(This post is missing and can not be restored)"
	},
	{
		"id": 15567,
		"title": "Unknown",
		"author_id": 0,
		"author_name": "Anonymous",
		"timestamp": "2004-12-31T22:00:00.000Z",
		"content": "(This post is missing and can not be restored)"
	},
	{
		"id": 15568,
		"title": "Unknown",
		"author_id": 0,
		"author_name": "Anonymous",
		"timestamp": "2004-12-31T22:00:00.000Z",
		"content": "(This post is missing and can not be restored)"
	},
	{
		"id": 15569,
		"title": "Unknown",
		"author_id": 0,
		"author_name": "Anonymous",
		"timestamp": "2004-12-31T22:00:00.000Z",
		"content": "(This post is missing and can not be restored)"
	},
	{
		"id": 15570,
		"title": "Unknown",
		"author_id": 0,
		"author_name": "Anonymous",
		"timestamp": "2004-12-31T22:00:00.000Z",
		"content": "(This post is missing and can not be restored)"
	},
	{
		"id": 15571,
		"title": "Unknown",
		"author_id": 0,
		"author_name": "Anonymous",
		"timestamp": "2004-12-31T22:00:00.000Z",
		"content": "(This post is missing and can not be restored)"
	},
	{
		"id": 15572,
		"title": "Unknown",
		"author_id": 0,
		"author_name": "Anonymous",
		"timestamp": "2004-12-31T22:00:00.000Z",
		"content": "(This post is missing and can not be restored)"
	},
	{
		"id": 15573,
		"title": "Unknown",
		"author_id": 0,
		"author_name": "Anonymous",
		"timestamp": "2004-12-31T22:00:00.000Z",
		"content": "(This post is missing and can not be restored)"
	},
	{
		"id": 15574,
		"title": "Unknown",
		"author_id": 0,
		"author_name": "Anonymous",
		"timestamp": "2004-12-31T22:00:00.000Z",
		"content": "(This post is missing and can not be restored)"
	},
	{
		"id": 15575,
		"title": "Unknown",
		"author_id": 0,
		"author_name": "Anonymous",
		"timestamp": "2004-12-31T22:00:00.000Z",
		"content": "(This post is missing and can not be restored)"
	},
	{
		"id": 15576,
		"title": "Unknown",
		"author_id": 0,
		"author_name": "Anonymous",
		"timestamp": "2004-12-31T22:00:00.000Z",
		"content": "(This post is missing and can not be restored)"
	},
	{
		"id": 15577,
		"title": "Unknown",
		"author_id": 0,
		"author_name": "Anonymous",
		"timestamp": "2004-12-31T22:00:00.000Z",
		"content": "(This post is missing and can not be restored)"
	},
	{
		"id": 15578,
		"title": "Unknown",
		"author_id": 0,
		"author_name": "Anonymous",
		"timestamp": "2004-12-31T22:00:00.000Z",
		"content": "(This post is missing and can not be restored)"
	},
	{
		"id": 15579,
		"title": "Unknown",
		"author_id": 0,
		"author_name": "Anonymous",
		"timestamp": "2004-12-31T22:00:00.000Z",
		"content": "(This post is missing and can not be restored)"
	},
	{
		"id": 15580,
		"title": "Unknown",
		"author_id": 0,
		"author_name": "Anonymous",
		"timestamp": "2004-12-31T22:00:00.000Z",
		"content": "(This post is missing and can not be restored)"
	},
	{
		"id": 15581,
		"title": "Unknown",
		"author_id": 0,
		"author_name": "Anonymous",
		"timestamp": "2004-12-31T22:00:00.000Z",
		"content": "(This post is missing and can not be restored)"
	},
	{
		"id": 15582,
		"title": "Unknown",
		"author_id": 0,
		"author_name": "Anonymous",
		"timestamp": "2004-12-31T22:00:00.000Z",
		"content": "(This post is missing and can not be restored)"
	},
	{
		"id": 15583,
		"title": "Unknown",
		"author_id": 0,
		"author_name": "Anonymous",
		"timestamp": "2004-12-31T22:00:00.000Z",
		"content": "(This post is missing and can not be restored)"
	},
	{
		"id": 15584,
		"title": "Unknown",
		"author_id": 0,
		"author_name": "Anonymous",
		"timestamp": "2004-12-31T22:00:00.000Z",
		"content": "(This post is missing and can not be restored)"
	},
	{
		"id": 15585,
		"title": "Unknown",
		"author_id": 0,
		"author_name": "Anonymous",
		"timestamp": "2004-12-31T22:00:00.000Z",
		"content": "(This post is missing and can not be restored)"
	},
	{
		"id": 15586,
		"title": "Unknown",
		"author_id": 0,
		"author_name": "Anonymous",
		"timestamp": "2004-12-31T22:00:00.000Z",
		"content": "(This post is missing and can not be restored)"
	},
	{
		"id": 580,
		"title": "Perilous Pursuit",
		"author_id": 1486548,
		"author_name": "ceilick",
		"timestamp": "2005-01-24T04:06:15.000Z",
		"content": "This is a keen 1 mod continuing the story of Goodbye Galaxy.  Most of the graphics and levels were done be me, while commander spleen worked on the patching, sound affects, and other fixes.  Have fun playing:<br /><br />Commander Keen in \"Goobye Galaxy!\" <br />Episode VI: Perilous Pursuit<br /><br />[url=http://jimsoft.spatang.com/keen/spleen/archive/pursuit.zip]jimsoft.spatang.com/keen/...ursuit.zip[/url]<br /><br />   -Ceilick-"
	}
]
