[
	{
		"id": 704,
		"title": "What year were you born in?",
		"author_id": 297417,
		"author_name": "rorie1983",
		"timestamp": "2005-05-24T02:27:47.000Z",
		"content": "What year were you born in?[url=http://www.dosvault.tk][img]http://venus.walagata.com/w/thedosvault/sig/tdv_banner.jpg[/img][/url]<br /><br /><b>WIPE OUT BUSH! WIPE OUT HOWARD!</b>"
	},
	{
		"id": 18700,
		"title": "Re: What year were you born in?",
		"author_id": 1485753,
		"author_name": "KeenRush",
		"timestamp": "2005-05-24T03:52:25.000Z",
		"content": "One Nine Eight Seven.<b>You hear in your mind: GAAARRRRRGG!</b>"
	},
	{
		"id": 18701,
		"title": "Re: What year were you born in?",
		"author_id": 1486240,
		"author_name": "grafix5000",
		"timestamp": "2005-05-24T06:51:42.000Z",
		"content": "I don't know, but it had four digits in it. :P<br /><br />It was probably 1991, though."
	},
	{
		"id": 18702,
		"title": "md spleen | copy c:\\games\\keen? spleen",
		"author_id": 1486940,
		"author_name": "CommanderSpleen",
		"timestamp": "2005-05-24T07:35:13.000Z",
		"content": "%ext pckb<br /><br />%patch $0834 $C0 $07<br /><br />%endCave assectatorem Ductoris Alacris <br /><br />\"You are so afraid to <i>live</i>--so afraid of <i>life itself</i>--that you've given up the <i>very nature of your being</i> in trade for security.\"<br />-CWG Book 3, Neale Donald Walsh<br /><br />[url=http://jimsoft.spatang.com/]JimSoft Lair[/url]"
	},
	{
		"id": 18703,
		"title": "well",
		"author_id": 1296984,
		"author_name": "XkyRauh2001",
		"timestamp": "2005-05-24T11:20:37.000Z",
		"content": "1983.  :-)"
	},
	{
		"id": 18704,
		"title": "Re",
		"author_id": 1215771,
		"author_name": "allstories",
		"timestamp": "2005-05-24T15:37:20.000Z",
		"content": "1989"
	},
	{
		"id": 18705,
		"title": "Re: Re",
		"author_id": 1486896,
		"author_name": "bp",
		"timestamp": "2005-05-24T21:36:29.000Z",
		"content": "1995,I am soooo young...[img]http://www.classicgaming.com/cc314/msgboard/emotikeen-shucks.gif[/img] bp ate the dopefish!"
	},
	{
		"id": 18706,
		"title": "Re: Re",
		"author_id": 1486477,
		"author_name": "Mr12000",
		"timestamp": "2005-05-25T01:07:29.000Z",
		"content": "1990"
	},
	{
		"id": 18707,
		"title": "Re: Re",
		"author_id": 1486477,
		"author_name": "Mr12000",
		"timestamp": "2005-05-25T01:09:59.000Z",
		"content": "bp... your making a 3d keen game at age 10?"
	},
	{
		"id": 18708,
		"title": ".",
		"author_id": 1486058,
		"author_name": "BlueIllusionX",
		"timestamp": "2005-05-25T02:34:24.000Z",
		"content": "1986 here"
	},
	{
		"id": 18709,
		"title": "Re: .",
		"author_id": 1485565,
		"author_name": "memsys",
		"timestamp": "2005-05-25T05:26:11.000Z",
		"content": "whee im from 1990[img]http://img.photobucket.com/albums/v177/memsys/goodorevilp.png[/img]"
	},
	{
		"id": 18710,
		"title": "Re: .",
		"author_id": 1485753,
		"author_name": "KeenRush",
		"timestamp": "2005-05-25T10:58:21.000Z",
		"content": "He's making 3D Keen game? [img]http://www.classicgaming.com/cc314/msgboard/emotikeen-confused.gif[/img] <br />Anyways, it's annoying how ten years back I had no access to internet.. GRRG. [img]http://www.classicgaming.com/cc314/msgboard/emotikeen-garg.gif[/img]  Not sure even if I had heard about it..<b>You hear in your mind: GAAARRRRRGG!</b>"
	},
	{
		"id": 18711,
		"title": "Re: .",
		"author_id": 1486896,
		"author_name": "bp",
		"timestamp": "2005-05-25T11:25:17.000Z",
		"content": "I am nine turning 10  sep./21/05bp ate the dopefish!"
	},
	{
		"id": 18712,
		"title": "Re: .",
		"author_id": 1486832,
		"author_name": "SpikeNexus",
		"timestamp": "2005-05-25T11:27:50.000Z",
		"content": "Ten years ago I was an eight year old un-super un-genious.<br /><br />I actually recall trying to connect to the internet ten years ago to get Cosmo cheats. Could never get on, for some reason..."
	},
	{
		"id": 18713,
		"title": "Re: .",
		"author_id": 1486477,
		"author_name": "Mr12000",
		"timestamp": "2005-05-25T14:16:55.000Z",
		"content": "KeenRush, the thread is here [url=http://p072.ezboard.com/fpubliccommanderkeenforumfrm17.showMessage?topicID=1110.topic]p072.ezboard.com/fpublicc...1110.topic[/url]"
	},
	{
		"id": 18714,
		"title": "Re: .",
		"author_id": 1486808,
		"author_name": "Galaxieretter",
		"timestamp": "2005-05-25T16:01:23.000Z",
		"content": "1987<br /><br />KeenRush, what month/day? I am July 8th.-----------------------<br />\"The Adventures of Commander Keen\" issue #1: coming soon."
	},
	{
		"id": 18715,
		"title": "Re: .",
		"author_id": 1485753,
		"author_name": "KeenRush",
		"timestamp": "2005-05-25T20:03:49.000Z",
		"content": "Mr12000, oops, forgot that topic entirely.. [img]http://www.classicgaming.com/cc314/msgboard/emotikeen-embarrassed.gif[/img] <br /><br />Hehe, I'm June 8th! Almost the same date, only two letters difference. [img]http://www.classicgaming.com/cc314/msgboard/emotikeen-smile.gif[/img] <b>You hear in your mind: GAAARRRRRGG!</b>"
	},
	{
		"id": 18716,
		"title": "Re: .",
		"author_id": 1486240,
		"author_name": "grafix5000",
		"timestamp": "2005-05-25T20:57:05.000Z",
		"content": "[quote]<b><i>Quote:</i></b>[hr]Almost the same date, only two letters difference. [img]http://www.classicgaming.com/cc314/msgboard/emotikeen-smile.gif[/img] [hr][/quote]<br />Or one month, depending on how you look at it."
	},
	{
		"id": 18717,
		"title": "Re: What year were you born in?",
		"author_id": 1486649,
		"author_name": "Gnostiscene",
		"timestamp": "2005-05-25T22:07:13.000Z",
		"content": "1990"
	},
	{
		"id": 18718,
		"title": "Re: What year were you born in?",
		"author_id": 180328,
		"author_name": "DivoKeen",
		"timestamp": "2005-05-25T23:38:48.000Z",
		"content": "1989 [img]http://www.classicgaming.com/cc314/msgboard/emotikeen-smile.gif[/img] -------------------------------<br />If something's HARD to do, then it's NOT worth doing. -Homer J. Simpson"
	},
	{
		"id": 18719,
		"title": "Re: What year were you born in?",
		"author_id": 1035697,
		"author_name": "0 UNFLEEXABLE 0",
		"timestamp": "2005-05-26T07:56:55.000Z",
		"content": "1989. I'm currently a 16 year old n0-life l0w life. [img]http://www.classicgaming.com/cc314/msgboard/emotikeen-smile.gif[/img] [img]http://www.geocities.com/miniopolis/soul.txt[/img]"
	},
	{
		"id": 18720,
		"title": "Re: What year were you born in?",
		"author_id": 1486892,
		"author_name": "PBoard",
		"timestamp": "2005-05-27T17:05:58.000Z",
		"content": "1992!!"
	},
	{
		"id": 18721,
		"title": "Re: What year were you born in?",
		"author_id": 1485741,
		"author_name": "Keen Xtreme",
		"timestamp": "2005-05-27T20:24:51.000Z",
		"content": "1989"
	},
	{
		"id": 18722,
		"title": "Re: What year were you born in?",
		"author_id": 1485994,
		"author_name": "Ultimo Spaz",
		"timestamp": "2005-05-29T12:13:16.000Z",
		"content": "1990The Keen... Revolution... Is.. Almost.. Here.. 05'"
	},
	{
		"id": 18723,
		"title": "Re: What year were you born in?",
		"author_id": 180328,
		"author_name": "DivoKeen",
		"timestamp": "2005-05-29T19:55:22.000Z",
		"content": "You can't get enough of these kinds of topics [img]http://www.classicgaming.com/cc314/msgboard/emotikeen-helmet.gif[/img] -------------------------------<br />If something's HARD to do, then it's NOT worth doing. -Homer J. Simpson"
	},
	{
		"id": 18724,
		"title": "Re: What year were you born in?",
		"author_id": 1485753,
		"author_name": "KeenRush",
		"timestamp": "2005-06-02T04:40:03.000Z",
		"content": "[img]http://www.classicgaming.com/cc314/msgboard/emotikeen-lol.gif[/img]  It's always fun to know the ages, as well it's quite surprising when someone you think \"must be at least 25\" happens to be 15.. [img]http://www.classicgaming.com/cc314/msgboard/emotikeen-smile.gif[/img]  As well, as this board gets new members they probably want to see new topics instead of opening some olde ones.<b>You hear in your mind: GAAARRRRRGG!</b>"
	},
	{
		"id": 18729,
		"title": "year",
		"author_id": 1486192,
		"author_name": "megakeen",
		"timestamp": "2007-07-25T17:28:48.000Z",
		"content": "1992"
	},
	{
		"id": 18725,
		"title": "Re: What year were you born in?",
		"author_id": 1486364,
		"author_name": "Xtraverse",
		"timestamp": "2007-07-26T02:17:05.000Z",
		"content": "from some topic in unofficial keen games:<br />[quote]<b><i>Quote:</i></b>[hr]i am only 15 [img]http://www.classicgaming.com/cc314/msgboard/emotikeen-no.gif[/img] [hr][/quote]<br /><br />uhh...[url=http://spatang.com/ck][img]http://spatang.com/ck/bannersm.jpg[/img][/url] [url=http://spatang.com/cosmo][img]http://spatang.com/cosmo/bannersm.jpg[/img][/url] [url=http://spatang.com/nukem][img]http://www.spatang.com/nukem/bannersm.jpg[/img][/url] [img]http://spatang.com/scrobblersig.php[/img]"
	},
	{
		"id": 18726,
		"title": "Re: What year were you born in?",
		"author_id": 360657,
		"author_name": "Commander Spleen",
		"timestamp": "2007-07-26T15:25:35.000Z",
		"content": "This thread seems to be glitching. There's supposedly been a reply by DaVince and Lava following Xtra, but only this reply has shown up..."
	},
	{
		"id": 18727,
		"title": "Re: What year were you born in?",
		"author_id": 338828,
		"author_name": "Shadow Master",
		"timestamp": "2007-07-30T15:43:36.000Z",
		"content": "'90. 'nuff said.------------------------------<br />[url=http://shadowm2006.sitesled.com/]My website[/url]<br />[url=http://p072.ezboard.com/fpubliccommanderkeenforumfrm20.showMessage?topicID=12.topic]Get Windows/Linux native LModKeen 2 with integrated FIN2BMP![/url]. You know you want to.<br />[url=http://shadowm2006.sitesled.com/meta/projectpage.htm]The META engine for 2D games[/url]."
	},
	{
		"id": 18730,
		"title": "Re: year",
		"author_id": 40038,
		"author_name": "DaVince21",
		"timestamp": "2007-07-30T16:08:38.000Z",
		"content": "test<br /><br />EDIT: WHOA! I can post! [img]http://www.classicgaming.com/cc314/msgboard/emotikeen-offended.gif[/img] <br /><br />1988, so I'm 19.____________<br />Don't see me as an ordinary man.<br />Even though I am an ordinary man.<br /><br />Ah, [url=http://DaVince.sitesled.com/]site.[/url]<br />Oh, and [url=http://www.tengusoft.net/]Team[/url]."
	},
	{
		"id": 18728,
		"title": "Re:",
		"author_id": 1485645,
		"author_name": "Q90",
		"timestamp": "2007-07-30T20:36:49.000Z",
		"content": "Late '89. I guess the \"late\" doesn't really matter though... holy shiza I just realized I'm almost in my 20s."
	}
]
