[
	{
		"id": 767,
		"title": "Flaose",
		"author_id": 1486085,
		"author_name": "eK",
		"timestamp": "2007-01-19T23:48:47.000Z",
		"content": "Flaose has returned from 2 years at Peru.<br /><br />I'll talk him to coming by and saying hi."
	},
	{
		"id": 19910,
		"title": "Re: Flaose",
		"author_id": 297097,
		"author_name": "grafix",
		"timestamp": "2007-01-20T00:06:28.000Z",
		"content": "I was going to post something to the effect of this being the second anniversary of his departure, and hoping he'd return soon, but decided against it. It's great to hear that he's back, and it'd be wonderful for him to pop in, even if he decides not to return to the community (as I would have thought he would, but you never know).[url=http://toxicsheep.com]toxicsheep.com[/url] | [url=http://commanderkeen.org]coming up next...[/url]"
	},
	{
		"id": 19911,
		"title": "Re: Flaose",
		"author_id": 1485695,
		"author_name": "Genius314",
		"timestamp": "2007-01-20T00:24:08.000Z",
		"content": "Wow, has it really been two years already?<br />He left right after I joined. So I've been here for two years... [img]http://www.classicgaming.com/cc314/msgboard/emotikeen-dopekeen.gif[/img] -Genius314<br />[url=http://planetck.spatang.com]PlanetCK[/url]"
	},
	{
		"id": 19912,
		"title": "yay",
		"author_id": 1296984,
		"author_name": "XkyRauh2001",
		"timestamp": "2007-01-20T04:33:44.000Z",
		"content": "Welcome back, Flaose.  <img src=\"https://groups.tapatalk-cdn.com/smilies/27135/1534636883.9457-smiley.gif?ttinline=true\"/>"
	},
	{
		"id": 19913,
		"title": "Re: yay",
		"author_id": 1485753,
		"author_name": "KeenRush",
		"timestamp": "2007-01-20T10:51:06.000Z",
		"content": "Woah, two years already! I can't believe it.. [img]http://www.classicgaming.com/cc314/msgboard/emotikeen-smoke2.gif[/img] <br /><br />Anyways, great to hear he has safely returned! Hopefully we'll see him around! Welcome back! [img]http://www.classicgaming.com/cc314/msgboard/emotikeen-smile.gif[/img] 3D Realms: \"Do you think there'll ever be a sequel to your game(s)?\"<br /><b>Tom Hall</b>: \"<i>If</i> I owned Keen, there sure would be. I <b>don't consider</b> that GBA game canon by any means.\""
	},
	{
		"id": 19914,
		"title": "Re: yay",
		"author_id": 989154,
		"author_name": "Djaser",
		"timestamp": "2007-01-20T19:39:45.000Z",
		"content": "I yet have to see him return, I guess he will but I'll wait for that moment.-----------------<br />[img]http://www.jamster.co.uk/s/jcw/img/logo_jamster_navi.gif[/img][img]http://www.jamster.co.uk/storage/view/335/0/cr/CrazyFrog___Axel_F_Falling.gif[/img]"
	},
	{
		"id": 19915,
		"title": "Re: yay",
		"author_id": 40038,
		"author_name": "DaVince21",
		"timestamp": "2007-01-21T22:05:14.000Z",
		"content": "I don't know Flaose yet, but welcome back. [img]http://www.classicgaming.com/cc314/msgboard/emotikeen-smile.gif[/img] ____________<br />Don't think of me as an ordinary man.<br /><br />Even though I am an ordinary man.<br /><br />Ah, [url=http://DaVince.sitesled.com/]site.[/url]"
	},
	{
		"id": 19916,
		"title": "error",
		"author_id": 1486085,
		"author_name": "eK",
		"timestamp": "2007-01-23T05:26:33.000Z",
		"content": "Haven't seen him since he stopped by... when I do, I'll send him over if he doesn't do it himself first."
	},
	{
		"id": 19917,
		"title": "Re: error",
		"author_id": 1486917,
		"author_name": "Flaose",
		"timestamp": "2007-01-24T03:49:39.000Z",
		"content": "*poof*<br /><br />Aha!  I had to unpack a few boxes to find my scrambled password (I had written it down) and here I am.--------------------<br />[url=http://www.classicgaming.com/cc314/]Cerebral Cortex 314[/url] - For All of your Commander Keen Needs.<br />[url=http://www.classicgaming.com/cc314/dave/joes.html]Eat at Joes[/url]"
	},
	{
		"id": 19918,
		"title": "Re:",
		"author_id": 338828,
		"author_name": "Shadow Master",
		"timestamp": "2007-01-24T04:26:59.000Z",
		"content": "Oh, my!! [img]http://www.classicgaming.com/cc314/msgboard/emotikeen-surprise.gif[/img] ------------------<br /><b>SM:</b> <i>\"I could go and write a page about the Theory of Relativity (or whatever it's called), but, what is the point if I don't know what the Theory of Relativity is?\"</i><br /><br />[url=http://shadowm2006.sitesled.com/]My website[/url]"
	},
	{
		"id": 19919,
		"title": "laosef(\"huzzah\");",
		"author_id": 360657,
		"author_name": "Commander Spleen",
		"timestamp": "2007-01-24T07:12:07.000Z",
		"content": "He lives! This calls for one thing, and one thing only...<br /><br /><b>MOSH PIT!</b>"
	},
	{
		"id": 19920,
		"title": "response",
		"author_id": 1296984,
		"author_name": "XkyRauh2001",
		"timestamp": "2007-01-24T07:14:41.000Z",
		"content": "Wha--Moshpit?  *Does his imitation of a Foob, turning to run, but smacks headlong into KeenRush, where he explodes in a shower of yellow surprise*  *Foob death noise*  <img src=\"http://www.classicgaming.com/cc314/msgboard/emotikeen-offended.gif?ttinline=true\"/><br /><br />How was your trip, Flaose?  Do you have pictures?  <img src=\"https://groups.tapatalk-cdn.com/smilies/27135/1534636883.9457-smiley.gif?ttinline=true\"/>"
	},
	{
		"id": 19921,
		"title": "*off topic vermin/poultry (?) deaths*",
		"author_id": 360657,
		"author_name": "Commander Spleen",
		"timestamp": "2007-01-24T07:17:55.000Z",
		"content": "[hr]<b>Xky</b> *Foob death noise*<br />[hr]Blast. Another minion down. Hehe, yellow surprise."
	},
	{
		"id": 19922,
		"title": "Re: response",
		"author_id": 1486917,
		"author_name": "Flaose",
		"timestamp": "2007-01-24T08:05:50.000Z",
		"content": "[quote]<b><i>Quote:</i></b>[hr]<i>Originally posted by: XkyRauh2001</i><br />How was your trip, Flaose? Do you have pictures? [img]http://www.classicgaming.com/cc314/msgboard/emotikeen-smile.gif[/img] [hr][/quote]<br /><br />You'd better believe it!  Probably close to 1000!  But...in good old film, not digital.--------------------<br />[url=http://www.classicgaming.com/cc314/]Cerebral Cortex 314[/url] - For All of your Commander Keen Needs.<br />[url=http://www.classicgaming.com/cc314/dave/joes.html]Eat at Joes[/url]"
	},
	{
		"id": 19923,
		"title": "Re: response",
		"author_id": 989154,
		"author_name": "Djaser",
		"timestamp": "2007-01-24T09:29:02.000Z",
		"content": "Perhaps you have a scanner?<br /><br />So welcome back, did you save any souls there?-----------------<br />[img]http://www.jamster.co.uk/s/jcw/img/logo_jamster_navi.gif[/img][img]http://www.jamster.co.uk/storage/view/335/0/cr/CrazyFrog___Axel_F_Falling.gif[/img]"
	},
	{
		"id": 19924,
		"title": "Re: response",
		"author_id": 1485753,
		"author_name": "KeenRush",
		"timestamp": "2007-01-24T11:52:24.000Z",
		"content": "Cool! [img]http://www.classicgaming.com/cc314/msgboard/emotikeen-smile.gif[/img]  Welcome back man!3D Realms: \"Do you think there'll ever be a sequel to your game(s)?\"<br /><b>Tom Hall</b>: \"<i>If</i> I owned Keen, there sure would be. I <b>don't consider</b> that GBA game canon by any means.\""
	},
	{
		"id": 19925,
		"title": "Re: response",
		"author_id": 1485832,
		"author_name": "Levelass",
		"timestamp": "2007-01-24T19:27:14.000Z",
		"content": "A thousand welcomes sir! You've been spoken of in only the highest terms, let us hope that you are seen around here often, that you may bring joy to others.<br /><br />*Sweeps up Xky and uses as confetti*<br />[img]http://img.photobucket.com/albums/v499/Nevad/menbun.gif[/img]<br /><br />Cute bunny!"
	},
	{
		"id": 19926,
		"title": "Re: response",
		"author_id": 1486364,
		"author_name": "Xtraverse",
		"timestamp": "2007-01-24T23:09:55.000Z",
		"content": "hey there.[url=http://spatang.com/ck][img]http://spatang.com/ck/bannersm.jpg[/img][/url] [url=http://spatang.com/cosmo][img]http://spatang.com/cosmo/bannersm.jpg[/img][/url] [url=http://spatang.com/nukem][img]http://www.spatang.com/nukem/bannersm.jpg[/img][/url] [img]http://spatang.com/scrobblersig.php[/img]"
	},
	{
		"id": 19927,
		"title": "Re: response",
		"author_id": 1485565,
		"author_name": "memsys",
		"timestamp": "2007-01-26T14:42:11.000Z",
		"content": "welcome back [img]http://www.classicgaming.com/cc314/msgboard/emotikeen-grin.gif[/img] [url=http://profile.xfire.com/memsys][img]http://miniprofile.xfire.com/bg/bg/type/2/memsys.png[/img][/url]"
	},
	{
		"id": 19928,
		"title": "Re: Flaose",
		"author_id": 338828,
		"author_name": "Shadow Master",
		"timestamp": "2007-01-26T15:40:45.000Z",
		"content": "Heh, Flaose, if you ever have spare time, you can go to the [url=http://wiki.commanderkeen.org]Keen Wiki[/url] and see what you can contribute there. [img]http://www.classicgaming.com/cc314/msgboard/emotikeen-smile.gif[/img]  I think the Keen community deserves a historic entry there, and an old member is perfect for that purpose.------------------<br /><b>SM:</b> <i>\"I could go and write a page about the Theory of Relativity (or whatever it's called), but, what is the point if I don't know what the Theory of Relativity is?\"</i><br /><br />[url=http://shadowm2006.sitesled.com/]My website[/url]"
	},
	{
		"id": 19929,
		"title": "Re: Flaose",
		"author_id": 1486239,
		"author_name": "ElecDude33",
		"timestamp": "2007-01-27T00:44:24.000Z",
		"content": "Greetings.------------------<br />Nothing in particular"
	},
	{
		"id": 19930,
		"title": "Re: Flaose",
		"author_id": 1486023,
		"author_name": "Too Much Spare Time",
		"timestamp": "2007-01-27T11:25:36.000Z",
		"content": "Hey hey, welcome back Flaose. I sometimes come by here to see how things are going. [img]http://www.classicgaming.com/cc314/msgboard/emotikeen-smile.gif[/img] ----------<br />www.StrifeStrips.com! Woot! We're back, baby!"
	},
	{
		"id": 19931,
		"title": "...",
		"author_id": 1486279,
		"author_name": "LordOfGlobox",
		"timestamp": "2007-01-29T16:10:12.000Z",
		"content": "Hullo again, Flaose."
	},
	{
		"id": 19932,
		"title": "Re: ...",
		"author_id": 989154,
		"author_name": "Djaser",
		"timestamp": "2007-01-29T17:01:43.000Z",
		"content": "This is the most disappointing topic ever on the pckf. -----------------<br />[img]http://www.jamster.co.uk/s/jcw/img/logo_jamster_navi.gif[/img][img]http://www.jamster.co.uk/storage/view/335/0/cr/CrazyFrog___Axel_F_Falling.gif[/img]"
	},
	{
		"id": 19933,
		"title": "Re: ...",
		"author_id": 1486808,
		"author_name": "Galaxieretter",
		"timestamp": "2007-01-29T17:57:19.000Z",
		"content": "I would have to agree with you there on that one, Djaser.-----------------------<br />The end of this post. You may stop reading now."
	},
	{
		"id": 19934,
		"title": "Re: ...",
		"author_id": 1485832,
		"author_name": "Levelass",
		"timestamp": "2007-01-29T19:30:49.000Z",
		"content": "I don't know, it's touching to see such a warm welcome from the community, it shows how much people care. I should hate to go to my school reunion in a decade's time and be ignored.<br />[img]http://img.photobucket.com/albums/v499/Nevad/menbun.gif[/img]<br /><br />Cute bunny!"
	},
	{
		"id": 19935,
		"title": "Re: ...",
		"author_id": 1485753,
		"author_name": "KeenRush",
		"timestamp": "2007-01-30T01:14:36.000Z",
		"content": "I definitely won't go to any school reunion.3D Realms: \"Do you think there'll ever be a sequel to your game(s)?\"<br /><b>Tom Hall</b>: \"<i>If</i> I owned Keen, there sure would be. I <b>don't consider</b> that GBA game canon by any means.\""
	}
]
